dataclouder_mongo/__init__.py
dataclouder_mongo/mongo.py
dataclouder_mongo/mongo_arrays.py
dataclouder_mongo-0.0.6.dist-info/METADATA
dataclouder_mongo-0.0.6.dist-info/WHEEL
dataclouder_mongo-0.0.6.dist-info/RECORD
