Metadata-Version: 2.3
Name: dataclouder-mongo
Version: 0.0.6
Summary: A library to improve mongo methods
Author: adamo figueroa
Author-email: adamo@dataclouder.com
Requires-Python: >=3.11
Classifier: Programming Language :: Python :: 3
Classifier: Programming Language :: Python :: 3.11
Classifier: Programming Language :: Python :: 3.12
Classifier: Programming Language :: Python :: 3.13
